litserve/__about__.py
litserve/__init__.py
litserve/__main__.py
litserve/api.py
litserve/cli.py
litserve/connector.py
litserve/constants.py
litserve/docker_builder.py
litserve/loggers.py
litserve/mcp.py
litserve/middlewares.py
litserve/python_client.py
litserve/server.py
litserve/utils.py
litserve/callbacks/__init__.py
litserve/callbacks/base.py
litserve/callbacks/defaults/__init__.py
litserve/callbacks/defaults/metric_callback.py
litserve/loops/__init__.py
litserve/loops/base.py
litserve/loops/continuous_batching_loop.py
litserve/loops/loops.py
litserve/loops/simple_loops.py
litserve/loops/streaming_loops.py
litserve/schema/__init__.py
litserve/schema/image.py
litserve/specs/__init__.py
litserve/specs/base.py
litserve/specs/openai.py
litserve/specs/openai_embedding.py
litserve/test_examples/__init__.py
litserve/test_examples/openai_embedding_spec_example.py
litserve/test_examples/openai_spec_example.py
litserve/test_examples/simple_example.py
litserve/transport/__init__.py
litserve/transport/base.py
litserve/transport/factory.py
litserve/transport/process_transport.py
litserve/transport/zmq_queue.py
litserve/transport/zmq_transport.py
litserve-0.2.16.dist-info/METADATA
litserve-0.2.16.dist-info/WHEEL
litserve-0.2.16.dist-info/entry_points.txt
litserve-0.2.16.dist-info/licenses/LICENSE
litserve-0.2.16.dist-info/RECORD
