Metadata-Version: 2.4
Name: litserve
Version: 0.2.16
Summary: Lightweight AI server.
Project-URL: Homepage, https://github.com/Lightning-AI/litserve
Project-URL: Bug Tracker, https://github.com/Lightning-AI/litserve/issues
Project-URL: Documentation, https://lightning-ai.github.io/litserve/
Project-URL: Source Code, https://github.com/Lightning-AI/litserve
Project-URL: Download, https://github.com/Lightning-AI/litserve
Author-email: "Lightning-AI et al." <community@lightning.ai>
License: Apache-2.0
License-File: LICENSE
Keywords: AI,deep learning,pytorch
Classifier: Development Status :: 4 - Beta
Classifier: Environment :: Console
Classifier: Intended Audience :: Developers
Classifier: License :: OSI Approved :: Apache Software License
Classifier: Natural Language :: English
Classifier: Operating System :: OS Independent
Classifier: Programming Language :: Python :: 3
Classifier: Programming Language :: Python :: 3.8
Classifier: Programming Language :: Python :: 3.9
Classifier: Programming Language :: Python :: 3.10
Classifier: Programming Language :: Python :: 3.11
Classifier: Programming Language :: Python :: 3.12
Classifier: Topic :: Scientific/Engineering :: Artificial Intelligence
Classifier: Topic :: Scientific/Engineering :: Information Analysis
Requires-Python: >=3.9
Requires-Dist: fastapi>=0.112
Requires-Dist: pyzmq>=22.0.0
Requires-Dist: uvicorn[standard]>=0.29.0
